[{"id":0,"avatar_url":"https://avatars1.githubusercontent.com/u/490779?v=4","login":"hasinhayder","name":"Hasin Hayder","followers":1842,"contribution":188},{"id":1,"avatar_url":"https://avatars1.githubusercontent.com/u/191543?v=4","login":"masnun","name":"Abu Ashraf Masnun","followers":961,"contribution":1025},{"id":2,"avatar_url":"https://avatars3.githubusercontent.com/u/153669?v=4","login":"tareq1988","name":"Tareq Hasan","followers":794,"contribution":657},{"id":3,"avatar_url":"https://avatars0.githubusercontent.com/u/3769029?v=4","login":"hasancse91","name":"Hasan Abdullah","followers":645,"contribution":386},{"id":4,"avatar_url":"https://avatars1.githubusercontent.com/u/932949?v=4","login":"aniruddha-adhikary","name":"Aniruddha Adhikary","followers":568,"contribution":342},{"id":5,"avatar_url":"https://avatars2.githubusercontent.com/u/765322?v=4","login":"theanam","name":"Anam Ahmed","followers":528,"contribution":1257},{"id":6,"avatar_url":"https://avatars2.githubusercontent.com/u/22605783?v=4","login":"arifulbgt4","name":"Ariful islam","followers":489,"contribution":64},{"id":7,"avatar_url":"https://avatars3.githubusercontent.com/u/2240000?v=4","login":"mugli","name":"Mehdi Hasan Khan","followers":452,"contribution":487},{"id":8,"avatar_url":"https://avatars3.githubusercontent.com/u/8012876?v=4","login":"manashmandal","name":"Manash Kumar Mandal","followers":445,"contribution":721},{"id":9,"avatar_url":"https://avatars0.githubusercontent.com/u/5456665?v=4","login":"MinhasKamal","name":"Minhas Kamal","followers":428,"contribution":11},{"id":0,"avatar_url":"https://avatars3.githubusercontent.com/u/8364221?v=4","login":"howtocode-com-bd","name":"howtocode.com.bd","followers":423,"contribution":14},{"id":1,"avatar_url":"https://avatars1.githubusercontent.com/u/11742254?v=4","login":"maateen","name":"Maksudur Rahman Maateen","followers":403,"contribution":698},{"id":2,"avatar_url":"https://avatars3.githubusercontent.com/u/831997?v=4","login":"me-shaon","name":"Ahmed shamim","followers":377,"contribution":161},{"id":3,"avatar_url":"https://avatars2.githubusercontent.com/u/19432983?v=4","login":"Arif-un","name":"Arif Uddin","followers":307,"contribution":64},{"id":4,"avatar_url":"https://avatars3.githubusercontent.com/u/3167309?v=4","login":"nahid","name":"Nahid Bin Azhar","followers":300,"contribution":117},{"id":5,"avatar_url":"https://avatars1.githubusercontent.com/u/3194741?v=4","login":"alamkanak","name":"Raquib-ul Alam (Kanak)","followers":294,"contribution":3},{"id":6,"avatar_url":"https://avatars0.githubusercontent.com/u/1708683?v=4","login":"sohelamin","name":"Sohel Amin","followers":293,"contribution":372},{"id":7,"avatar_url":"https://avatars0.githubusercontent.com/u/9676798?v=4","login":"thedevsaddam","name":"Saddam H","followers":280,"contribution":341},{"id":8,"avatar_url":"https://avatars2.githubusercontent.com/u/5650785?v=4","login":"s4kibs4mi","name":"Sakib Sami","followers":278,"contribution":150},{"id":9,"avatar_url":"https://avatars0.githubusercontent.com/u/1235888?v=4","login":"sarim","name":"Sarim Khan","followers":278,"contribution":27}]