[{"id":0,"avatar_url":"https://avatars3.githubusercontent.com/u/47313?v=4","login":"fabpot","name":"Fabien Potencier","followers":9679,"contribution":12802},{"id":1,"avatar_url":"https://avatars3.githubusercontent.com/u/76661?v=4","login":"ageron","name":"Aurélien Geron","followers":5145,"contribution":402},{"id":2,"avatar_url":"https://avatars2.githubusercontent.com/u/92794?v=4","login":"cyrilmottier","name":"Cyril Mottier","followers":4221,"contribution":7},{"id":3,"avatar_url":"https://avatars2.githubusercontent.com/u/5754972?v=4","login":"florent37","name":"Florent CHAMPIGNY","followers":3398,"contribution":57},{"id":4,"avatar_url":"https://avatars1.githubusercontent.com/u/395137?v=4","login":"Grafikart","name":"Jonathan","followers":3195,"contribution":177},{"id":5,"avatar_url":"https://avatars0.githubusercontent.com/u/89061?v=4","login":"ogrisel","name":"Olivier Grisel","followers":2838,"contribution":785},{"id":6,"avatar_url":"https://avatars2.githubusercontent.com/u/7819248?v=4","login":"x0rz","name":null,"followers":2739,"contribution":9},{"id":7,"avatar_url":"https://avatars3.githubusercontent.com/u/4429434?v=4","login":"flavienlaurent","name":"Flavien Laurent","followers":2478,"contribution":2},{"id":8,"avatar_url":"https://avatars0.githubusercontent.com/u/2798204?v=4","login":"Akryum","name":"Guillaume Chau","followers":2431,"contribution":273},{"id":9,"avatar_url":"https://avatars3.githubusercontent.com/u/845425?v=4","login":"SamyPesse","name":"Samy Pessé","followers":2382,"contribution":1526},{"id":0,"avatar_url":"https://avatars2.githubusercontent.com/u/124872?v=4","login":"jedisct1","name":"Frank Denis","followers":2218,"contribution":3533},{"id":1,"avatar_url":"https://avatars3.githubusercontent.com/u/1268691?v=4","login":"juliangarnier","name":"Julian Garnier","followers":2184,"contribution":268},{"id":2,"avatar_url":"https://avatars0.githubusercontent.com/u/20851561?v=4","login":"simplesteph","name":"Stephane Maarek","followers":2027,"contribution":84},{"id":3,"avatar_url":"https://avatars3.githubusercontent.com/u/99944?v=4","login":"fzaninotto","name":"Francois Zaninotto","followers":1843,"contribution":2008},{"id":4,"avatar_url":"https://avatars3.githubusercontent.com/u/2625526?v=4","login":"romainfrancois","name":"Romain François","followers":1756,"contribution":1405},{"id":5,"avatar_url":"https://avatars2.githubusercontent.com/u/233706?v=4","login":"mblondel","name":"Mathieu Blondel","followers":1711,"contribution":36},{"id":6,"avatar_url":"https://avatars1.githubusercontent.com/u/2307945?v=4","login":"gentilkiwi","name":"Benjamin DELPY","followers":1680,"contribution":24},{"id":7,"avatar_url":"https://avatars0.githubusercontent.com/u/439401?v=4","login":"stof","name":"Christophe Coevoet","followers":1641,"contribution":3509},{"id":8,"avatar_url":"https://avatars0.githubusercontent.com/u/664177?v=4","login":"posva","name":"Eduardo San Martin Morote","followers":1595,"contribution":1674},{"id":9,"avatar_url":"https://avatars2.githubusercontent.com/u/991046?v=4","login":"JonathanSalwan","name":"Jonathan Salwan","followers":1581,"contribution":365}]