[{"id":0,"avatar_url":"https://avatars1.githubusercontent.com/u/74385?v=4","login":"rstacruz","name":"Rico Sta. Cruz","followers":4317,"contribution":4604},{"id":1,"avatar_url":"https://avatars1.githubusercontent.com/u/1670421?v=4","login":"mithi","name":"Mithi Sevilla","followers":611,"contribution":469},{"id":2,"avatar_url":"https://avatars3.githubusercontent.com/u/2687997?v=4","login":"yajra","name":"Arjay Angeles","followers":566,"contribution":722},{"id":3,"avatar_url":"https://avatars0.githubusercontent.com/u/19164950?v=4","login":"jrGabrillo","name":"Rufo N. Gabrillo Jr.","followers":427,"contribution":4},{"id":4,"avatar_url":"https://avatars0.githubusercontent.com/u/5098765?v=4","login":"carl-alberto","name":"Carl Alberto","followers":416,"contribution":241},{"id":5,"avatar_url":"https://avatars2.githubusercontent.com/u/1888261?v=4","login":"silverbux","name":"Alex Quiambao","followers":370,"contribution":1696},{"id":6,"avatar_url":"https://avatars3.githubusercontent.com/u/29855143?v=4","login":"erafaelmanuel","name":"Rafael Manuel","followers":352,"contribution":9},{"id":7,"avatar_url":"https://avatars0.githubusercontent.com/u/26679?v=4","login":"marksteve","name":"Mark Steve Samson","followers":280,"contribution":2418},{"id":8,"avatar_url":"https://avatars1.githubusercontent.com/u/24869?v=4","login":"pageman","name":"Paul Pajo","followers":238,"contribution":2},{"id":9,"avatar_url":"https://avatars3.githubusercontent.com/u/12311971?v=4","login":"LordDashMe","name":"Joshua Clifford Reyes","followers":233,"contribution":1523},{"id":0,"avatar_url":"https://avatars1.githubusercontent.com/u/8848769?v=4","login":"roatienza","name":"Rowel Atienza","followers":205,"contribution":419},{"id":1,"avatar_url":"https://avatars0.githubusercontent.com/u/3483615?v=4","login":"shipcod3","name":"Jay Turla","followers":197,"contribution":63},{"id":2,"avatar_url":"https://avatars0.githubusercontent.com/u/838783?v=4","login":"ctrlcctrlv","name":"Fredrick Brennan","followers":196,"contribution":347},{"id":3,"avatar_url":"https://avatars3.githubusercontent.com/u/110625?v=4","login":"zakame","name":"Zak B. Elep","followers":187,"contribution":731},{"id":4,"avatar_url":"https://avatars3.githubusercontent.com/u/483547?v=4","login":"six519","name":"Ferdinand E. Silva","followers":182,"contribution":87},{"id":5,"avatar_url":"https://avatars3.githubusercontent.com/u/743603?v=4","login":"anchetaWern","name":"Wern Ancheta","followers":180,"contribution":618},{"id":6,"avatar_url":"https://avatars2.githubusercontent.com/u/5106887?v=4","login":"junedomingo","name":"June Domingo","followers":172,"contribution":4},{"id":7,"avatar_url":"https://avatars3.githubusercontent.com/u/7972655?v=4","login":"ivanceras","name":"Jovansonlee Cesar","followers":155,"contribution":907},{"id":8,"avatar_url":"https://avatars1.githubusercontent.com/u/1993075?v=4","login":"jaggy","name":"Jaggy","followers":154,"contribution":4026},{"id":9,"avatar_url":"https://avatars3.githubusercontent.com/u/16072259?v=4","login":"ArjunAranetaCodes","name":"MoreCodes","followers":142,"contribution":1291},{"id":0,"avatar_url":"https://avatars2.githubusercontent.com/u/7193634?v=4","login":"clrke","name":"Clarke Benedict Tapay Plumo","followers":140,"contribution":40},{"id":1,"avatar_url":"https://avatars2.githubusercontent.com/u/29720341?v=4","login":"ncleshyne","name":"Nicole Shayne Elim","followers":139,"contribution":0},{"id":2,"avatar_url":"https://avatars0.githubusercontent.com/u/12949683?v=4","login":"ljvmiranda921","name":"Lj Miranda","followers":139,"contribution":1987},{"id":3,"avatar_url":"https://avatars3.githubusercontent.com/u/5093058?v=4","login":"srph","name":"Kier Borromeo","followers":125,"contribution":1926},{"id":4,"avatar_url":"https://avatars2.githubusercontent.com/u/2481?v=4","login":"jasontorres","name":"Jason Torres","followers":122,"contribution":1479},{"id":5,"avatar_url":"https://avatars2.githubusercontent.com/u/4887598?v=4","login":"bradpotts","name":"Bradley J Potts","followers":120,"contribution":1992},{"id":6,"avatar_url":"https://avatars3.githubusercontent.com/u/458310?v=4","login":"jamesflorentino","name":"James Florentino","followers":114,"contribution":1289},{"id":7,"avatar_url":"https://avatars3.githubusercontent.com/u/14976516?v=4","login":"sr229","name":"Ayane Satomi","followers":113,"contribution":1837},{"id":8,"avatar_url":"https://avatars0.githubusercontent.com/u/1428598?v=4","login":"arnellebalane","name":"Arnelle Balane","followers":107,"contribution":2370},{"id":9,"avatar_url":"https://avatars2.githubusercontent.com/u/26832583?v=4","login":"cr4shcod3","name":"Jerald Dale","followers":103,"contribution":9},{"id":0,"avatar_url":"https://avatars1.githubusercontent.com/u/224404?v=4","login":"genediazjr","name":"Gene Diaz","followers":98,"contribution":94},{"id":1,"avatar_url":"https://avatars2.githubusercontent.com/u/886059?v=4","login":"MicahZoltu","name":"Micah Zoltu","followers":95,"contribution":712},{"id":2,"avatar_url":"https://avatars2.githubusercontent.com/u/79355?v=4","login":"dyu","name":"David Yu","followers":94,"contribution":101},{"id":3,"avatar_url":"https://avatars0.githubusercontent.com/u/157258?v=4","login":"radamanthus","name":"Radamanthus Batnag","followers":93,"contribution":97},{"id":4,"avatar_url":"https://avatars3.githubusercontent.com/u/1909444?v=4","login":"codemickeycode","name":"Micaela Reyes","followers":92,"contribution":60},{"id":5,"avatar_url":"https://avatars1.githubusercontent.com/u/7933430?v=4","login":"melvincabatuan","name":"Melvin Cabatuan","followers":91,"contribution":97},{"id":6,"avatar_url":"https://avatars3.githubusercontent.com/u/3293438?v=4","login":"rncrecario","name":"Reg Recario","followers":87,"contribution":0},{"id":7,"avatar_url":"https://avatars1.githubusercontent.com/u/6243?v=4","login":"meatcoder","name":"Sim Domingo","followers":84,"contribution":1503},{"id":8,"avatar_url":"https://avatars1.githubusercontent.com/u/117320?v=4","login":"MrValdez","name":"MrValdez","followers":83,"contribution":26},{"id":9,"avatar_url":"https://avatars2.githubusercontent.com/u/1033611?v=4","login":"bfintal","name":"Benjamin Intal","followers":83,"contribution":555},{"id":0,"avatar_url":"https://avatars0.githubusercontent.com/u/49830?v=4","login":"marconi","name":"Marconi Moreto Jr","followers":82,"contribution":54},{"id":1,"avatar_url":"https://avatars2.githubusercontent.com/u/5498919?v=4","login":"darryldecode","name":"darryl fernandez","followers":81,"contribution":316},{"id":2,"avatar_url":"https://avatars3.githubusercontent.com/u/3839684?v=4","login":"adonespitogo","name":"Adones Pitogo","followers":79,"contribution":312},{"id":3,"avatar_url":"https://avatars3.githubusercontent.com/u/2645718?v=4","login":"tjmonsi","name":"Toni-Jan Keith Monserrat","followers":78,"contribution":305},{"id":4,"avatar_url":"https://avatars3.githubusercontent.com/u/5047?v=4","login":"ngpestelos","name":"Nestor G Pestelos Jr","followers":78,"contribution":9},{"id":5,"avatar_url":"https://avatars1.githubusercontent.com/u/1166928?v=4","login":"jaunesarmiento","name":"Jaune Sarmiento","followers":77,"contribution":860},{"id":6,"avatar_url":"https://avatars0.githubusercontent.com/u/53690?v=4","login":"avendael","name":"Evan Dale Aromin","followers":76,"contribution":169},{"id":7,"avatar_url":"https://avatars1.githubusercontent.com/u/74308?v=4","login":"keikun17","name":"Cakey | Buddy Magsipoc","followers":76,"contribution":5},{"id":8,"avatar_url":"https://avatars3.githubusercontent.com/u/6779285?v=4","login":"MinecrafterPH","name":"Anton M.","followers":75,"contribution":0},{"id":9,"avatar_url":"https://avatars3.githubusercontent.com/u/1457730?v=4","login":"gjaldon","name":"Gabriel Jaldon","followers":74,"contribution":101},{"id":0,"avatar_url":"https://avatars3.githubusercontent.com/u/427738?v=4","login":"jpanganiban","name":"Jesse Panganiban","followers":73,"contribution":0},{"id":1,"avatar_url":"https://avatars1.githubusercontent.com/u/376472?v=4","login":"terenceponce","name":"Terence Ponce","followers":73,"contribution":179},{"id":2,"avatar_url":"https://avatars3.githubusercontent.com/u/2346301?v=4","login":"Temoto-kun","name":"Allan Crisostomo","followers":73,"contribution":363},{"id":3,"avatar_url":"https://avatars3.githubusercontent.com/u/13049130?v=4","login":"sorxrob","name":"Robert Anthonie","followers":72,"contribution":61},{"id":4,"avatar_url":"https://avatars1.githubusercontent.com/u/72819?v=4","login":"zenweasel","name":"Brent Hoover","followers":72,"contribution":1848},{"id":5,"avatar_url":"https://avatars0.githubusercontent.com/u/657249?v=4","login":"stormwild","name":"Alexander R Torrijos","followers":72,"contribution":317},{"id":6,"avatar_url":"https://avatars2.githubusercontent.com/u/16146873?v=4","login":"codegracie","name":"Grace Sojor","followers":71,"contribution":0},{"id":7,"avatar_url":"https://avatars3.githubusercontent.com/u/7943223?v=4","login":"diezcami","name":"Camille Diez","followers":67,"contribution":0},{"id":8,"avatar_url":"https://avatars3.githubusercontent.com/u/4339240?v=4","login":"rmrhz","name":"rm \"rhz\"","followers":67,"contribution":696},{"id":9,"avatar_url":"https://avatars1.githubusercontent.com/u/8457470?v=4","login":"johnpaulada","name":"John Paul Ada","followers":67,"contribution":117}]