[{"id":0,"avatar_url":"https://avatars3.githubusercontent.com/u/193136?v=4","login":"dtinth","name":"Thai Pangsakulyanont","followers":1037,"contribution":4086},{"id":1,"avatar_url":"https://avatars0.githubusercontent.com/u/522007?v=4","login":"verekia","name":"Jonathan Verrecchia","followers":937,"contribution":1614},{"id":2,"avatar_url":"https://avatars0.githubusercontent.com/u/141232?v=4","login":"antonmedv","name":"Anton Medvedev","followers":881,"contribution":1512},{"id":3,"avatar_url":"https://avatars2.githubusercontent.com/u/67157?v=4","login":"grugq","name":"thaddeus t. grugq","followers":857,"contribution":6},{"id":4,"avatar_url":"https://avatars1.githubusercontent.com/u/1949576?v=4","login":"akexorcist","name":"Akexorcist","followers":593,"contribution":130},{"id":5,"avatar_url":"https://avatars2.githubusercontent.com/u/61659?v=4","login":"nuuneoi","name":"Sittiphol Phanvilai","followers":564,"contribution":45},{"id":6,"avatar_url":"https://avatars1.githubusercontent.com/u/25113?v=4","login":"up1","name":"Somkiat Puisungnoen","followers":523,"contribution":1396},{"id":7,"avatar_url":"https://avatars0.githubusercontent.com/u/2123375?v=4","login":"lukechilds","name":"Luke Childs","followers":499,"contribution":1486},{"id":8,"avatar_url":"https://avatars0.githubusercontent.com/u/8029346?v=4","login":"Jeiwan","name":"Ivan Kuznetsov","followers":394,"contribution":2070},{"id":9,"avatar_url":"https://avatars3.githubusercontent.com/u/1352296?v=4","login":"worawit","name":"Worawit Wang","followers":318,"contribution":0},{"id":0,"avatar_url":"https://avatars1.githubusercontent.com/u/1763410?v=4","login":"jirawatee","name":"Jirawat Karanwittayakarn","followers":310,"contribution":143},{"id":1,"avatar_url":"https://avatars0.githubusercontent.com/u/8615768?v=4","login":"tarek360","name":"Ahmed Tarek","followers":307,"contribution":169},{"id":2,"avatar_url":"https://avatars1.githubusercontent.com/u/282408?v=4","login":"pierrejoye","name":"Pierre Joye","followers":305,"contribution":13},{"id":3,"avatar_url":"https://avatars1.githubusercontent.com/u/4714175?v=4","login":"phoomparin","name":"Phoomparin Mano","followers":299,"contribution":1089},{"id":4,"avatar_url":"https://avatars2.githubusercontent.com/u/10666?v=4","login":"chanwit","name":"Chanwit Kaewkasi","followers":297,"contribution":462},{"id":5,"avatar_url":"https://avatars3.githubusercontent.com/u/3608783?v=4","login":"PoomSmart","name":"Thatchapon Unprasert","followers":286,"contribution":491},{"id":6,"avatar_url":"https://avatars0.githubusercontent.com/u/1855019?v=4","login":"Phonbopit","name":"Chai Phonbopit","followers":267,"contribution":1688},{"id":7,"avatar_url":"https://avatars1.githubusercontent.com/u/5194767?v=4","login":"b-mueller","name":"Bernhard Mueller","followers":263,"contribution":1569},{"id":8,"avatar_url":"https://avatars0.githubusercontent.com/u/6111610?v=4","login":"acoshift","name":"Thanatat Tamtan","followers":257,"contribution":982},{"id":9,"avatar_url":"https://avatars0.githubusercontent.com/u/1006420?v=4","login":"jerriep","name":"Jerrie Pelser","followers":254,"contribution":212}]