[{"id":0,"avatar_url":"https://avatars2.githubusercontent.com/u/25254?v=4","login":"tj","name":"TJ Holowaychuk","followers":41244,"contribution":333},{"id":1,"avatar_url":"https://avatars0.githubusercontent.com/u/1655968?v=4","login":"toddmotto","name":"Todd Motto","followers":7451,"contribution":2600},{"id":2,"avatar_url":"https://avatars3.githubusercontent.com/u/439365?v=4","login":"daneden","name":"Daniel Eden","followers":5730,"contribution":596},{"id":3,"avatar_url":"https://avatars0.githubusercontent.com/u/13700?v=4","login":"remy","name":"Remy Sharp","followers":5529,"contribution":1460},{"id":4,"avatar_url":"https://avatars2.githubusercontent.com/u/546885?v=4","login":"nicklockwood","name":"Nick Lockwood","followers":5262,"contribution":2563},{"id":5,"avatar_url":"https://avatars3.githubusercontent.com/u/6673982?v=4","login":"MichalPaszkiewicz","name":"Michal Paszkiewicz","followers":5020,"contribution":210},{"id":6,"avatar_url":"https://avatars2.githubusercontent.com/u/175697?v=4","login":"jgilfelt","name":"Jeff Gilfelt","followers":4596,"contribution":1029},{"id":7,"avatar_url":"https://avatars1.githubusercontent.com/u/17011?v=4","login":"jskeet","name":"Jon Skeet","followers":4505,"contribution":3118},{"id":8,"avatar_url":"https://avatars2.githubusercontent.com/u/751944?v=4","login":"csswizardry","name":"Harry Roberts","followers":4377,"contribution":322},{"id":9,"avatar_url":"https://avatars1.githubusercontent.com/u/1254808?v=4","login":"jgthms","name":"Jeremy Thomas","followers":3730,"contribution":163},{"id":0,"avatar_url":"https://avatars3.githubusercontent.com/u/6792642?v=4","login":"sebastianruder","name":"Sebastian Ruder","followers":3632,"contribution":117},{"id":1,"avatar_url":"https://avatars1.githubusercontent.com/u/1383811?v=4","login":"mattdesl","name":"Matt DesLauriers","followers":3283,"contribution":3047},{"id":2,"avatar_url":"https://avatars2.githubusercontent.com/u/352556?v=4","login":"nickbutcher","name":"Nick Butcher","followers":2773,"contribution":236},{"id":3,"avatar_url":"https://avatars2.githubusercontent.com/u/336005?v=4","login":"keyboardsurfer","name":"Ben Weiss","followers":2770,"contribution":105},{"id":4,"avatar_url":"https://avatars0.githubusercontent.com/u/432536?v=4","login":"jspahrsummers","name":"Justin Spahr-Summers","followers":2729,"contribution":4555},{"id":5,"avatar_url":"https://avatars1.githubusercontent.com/u/1525924?v=4","login":"emilsjolander","name":"Emil Sjölander","followers":2729,"contribution":324},{"id":6,"avatar_url":"https://avatars3.githubusercontent.com/u/194400?v=4","login":"nelsonic","name":"Nelson","followers":2679,"contribution":3345},{"id":7,"avatar_url":"https://avatars2.githubusercontent.com/u/730395?v=4","login":"lucasr","name":"Lucas Rocha","followers":2662,"contribution":0},{"id":8,"avatar_url":"https://avatars1.githubusercontent.com/u/2998890?v=4","login":"florina-muntenescu","name":"Florina Muntenescu","followers":2608,"contribution":309},{"id":9,"avatar_url":"https://avatars0.githubusercontent.com/u/207870?v=4","login":"daylerees","name":"Dayle Rees","followers":2514,"contribution":1129},{"id":0,"avatar_url":"https://avatars1.githubusercontent.com/u/124075?v=4","login":"dsyer","name":"Dave Syer","followers":2473,"contribution":870},{"id":1,"avatar_url":"https://avatars3.githubusercontent.com/u/1706326?v=4","login":"alvarotrigo","name":"Álvaro","followers":2373,"contribution":980},{"id":2,"avatar_url":"https://avatars3.githubusercontent.com/u/31223?v=4","login":"jasondavies","name":"Jason Davies","followers":2352,"contribution":21},{"id":3,"avatar_url":"https://avatars2.githubusercontent.com/u/617438?v=4","login":"paullewis","name":"Paul Lewis","followers":2352,"contribution":349},{"id":4,"avatar_url":"https://avatars3.githubusercontent.com/u/346311?v=4","login":"soulwire","name":"Justin Windle","followers":2306,"contribution":0},{"id":5,"avatar_url":"https://avatars2.githubusercontent.com/u/164476?v=4","login":"photonstorm","name":"Richard Davey","followers":2221,"contribution":2679},{"id":6,"avatar_url":"https://avatars2.githubusercontent.com/u/1060?v=4","login":"andrew","name":"Andrew Nesbitt","followers":2161,"contribution":1091},{"id":7,"avatar_url":"https://avatars0.githubusercontent.com/u/5274?v=4","login":"caolan","name":"Caolan McMahon","followers":2150,"contribution":95},{"id":8,"avatar_url":"https://avatars0.githubusercontent.com/u/6391776?v=4","login":"nikitavoloboev","name":"Nikita Voloboev","followers":1931,"contribution":2419},{"id":9,"avatar_url":"https://avatars3.githubusercontent.com/u/236767?v=4","login":"sdiehl","name":"Stephen Diehl","followers":1897,"contribution":732},{"id":0,"avatar_url":"https://avatars3.githubusercontent.com/u/190200?v=4","login":"twostraws","name":"Paul Hudson","followers":1883,"contribution":1676},{"id":1,"avatar_url":"https://avatars3.githubusercontent.com/u/4069972?v=4","login":"VagrantStory","name":"mohammad","followers":1872,"contribution":0},{"id":2,"avatar_url":"https://avatars2.githubusercontent.com/u/647359?v=4","login":"tomchristie","name":"Tom Christie","followers":1859,"contribution":2246},{"id":3,"avatar_url":"https://avatars1.githubusercontent.com/u/44164?v=4","login":"kylef","name":"Kyle Fuller","followers":1851,"contribution":3188},{"id":4,"avatar_url":"https://avatars1.githubusercontent.com/u/9906?v=4","login":"passy","name":"Pascal Hartig","followers":1822,"contribution":1314},{"id":5,"avatar_url":"https://avatars2.githubusercontent.com/u/17880?v=4","login":"bodil","name":"Bodil Stokke","followers":1699,"contribution":515},{"id":6,"avatar_url":"https://avatars1.githubusercontent.com/u/234957?v=4","login":"surma","name":"Surma","followers":1694,"contribution":2648},{"id":7,"avatar_url":"https://avatars2.githubusercontent.com/u/125011?v=4","login":"MikeMcQuaid","name":"Mike McQuaid","followers":1692,"contribution":5898},{"id":8,"avatar_url":"https://avatars3.githubusercontent.com/u/535942?v=4","login":"g0tmi1k","name":"g0tmi1k","followers":1687,"contribution":220},{"id":9,"avatar_url":"https://avatars0.githubusercontent.com/u/1519870?v=4","login":"trueadm","name":"Dominic Gannaway","followers":1638,"contribution":876},{"id":0,"avatar_url":"https://avatars2.githubusercontent.com/u/33135?v=4","login":"akrabat","name":"Rob Allen","followers":1628,"contribution":588},{"id":1,"avatar_url":"https://avatars0.githubusercontent.com/u/3879281?v=4","login":"hitherejoe","name":"Joe Birch","followers":1608,"contribution":225},{"id":2,"avatar_url":"https://avatars1.githubusercontent.com/u/694641?v=4","login":"IanLunn","name":"Ian Lunn","followers":1593,"contribution":3252},{"id":3,"avatar_url":"https://avatars2.githubusercontent.com/u/8669769?v=4","login":"dli","name":"David Li","followers":1583,"contribution":0},{"id":4,"avatar_url":"https://avatars0.githubusercontent.com/u/144873?v=4","login":"mattgemmell","name":"Matt Gemmell","followers":1528,"contribution":1},{"id":5,"avatar_url":"https://avatars0.githubusercontent.com/u/27544?v=4","login":"ept","name":"Martin Kleppmann","followers":1480,"contribution":460},{"id":6,"avatar_url":"https://avatars1.githubusercontent.com/u/58276?v=4","login":"tomnomnom","name":"Tom Hudson","followers":1475,"contribution":189},{"id":7,"avatar_url":"https://avatars2.githubusercontent.com/u/6715118?v=4","login":"ShangtongZhang","name":"Shangtong Zhang","followers":1472,"contribution":127},{"id":8,"avatar_url":"https://avatars3.githubusercontent.com/u/101659?v=4","login":"matryer","name":"Mat Ryer","followers":1466,"contribution":309},{"id":9,"avatar_url":"https://avatars2.githubusercontent.com/u/973543?v=4","login":"gajus","name":"Gajus Kuizinas","followers":1466,"contribution":1722},{"id":0,"avatar_url":"https://avatars0.githubusercontent.com/u/1098110?v=4","login":"ColinEberhardt","name":"Colin Eberhardt","followers":1399,"contribution":348},{"id":1,"avatar_url":"https://avatars3.githubusercontent.com/u/731885?v=4","login":"spite","name":"Jaume Sanchez","followers":1378,"contribution":275},{"id":2,"avatar_url":"https://avatars0.githubusercontent.com/u/45510?v=4","login":"PaulKinlan","name":"Paul Kinlan","followers":1358,"contribution":928},{"id":3,"avatar_url":"https://avatars3.githubusercontent.com/u/8780?v=4","login":"weavejester","name":"James Reeves","followers":1348,"contribution":372},{"id":4,"avatar_url":"https://avatars0.githubusercontent.com/u/933874?v=4","login":"StylingAndroid","name":"Mark Allison","followers":1322,"contribution":737},{"id":5,"avatar_url":"https://avatars1.githubusercontent.com/u/1671?v=4","login":"scrooloose","name":"Martin Grenfell","followers":1282,"contribution":108},{"id":6,"avatar_url":"https://avatars1.githubusercontent.com/u/101513?v=4","login":"ErisDS","name":"Hannah Wolfe","followers":1244,"contribution":822},{"id":7,"avatar_url":"https://avatars2.githubusercontent.com/u/9265?v=4","login":"jcoglan","name":"James Coglan","followers":1197,"contribution":551},{"id":8,"avatar_url":"https://avatars0.githubusercontent.com/u/1260646?v=4","login":"ForbesLindesay","name":"Forbes Lindesay","followers":1170,"contribution":362},{"id":9,"avatar_url":"https://avatars2.githubusercontent.com/u/149211?v=4","login":"mikedewar","name":"Mike Dewar","followers":1150,"contribution":6}]